kustopy/KustoPyClient.py
kustopy/__init__.py
kustopy-1.2.8.dist-info/METADATA
kustopy-1.2.8.dist-info/PKG-INFO-CH3076503W2
kustopy-1.2.8.dist-info/WHEEL
kustopy-1.2.8.dist-info/entry_points.txt
kustopy-1.2.8.dist-info/top_level.txt
kustopy-1.2.8.dist-info/RECORD
