Metadata-Version: 2.1
Name: kustopy
Version: 1.2.8
Summary: Query and Ingestion Client for Azure using Python
Home-page: https://github.com/tillfurger/kustopy
Author: Till Furger
Author-email: till@furger.net
License: MIT
Platform: UNKNOWN
Classifier: License :: OSI Approved :: MIT License
Classifier: Programming Language :: Python :: 3
Classifier: Programming Language :: Python :: 3.7
Requires-Dist: azure-kusto-data
Requires-Dist: azure-kusto-ingest
Requires-Dist: pandas
Requires-Dist: pyspark
